{
  "app.loading": "Wird geladen",
  "app.menu-button.alt": "NENO Logo und Menü-Button",
  "app.pinned-notes-placeholder": "Hier erscheinen deine angepinnten Notizen",
  "app.title": "NENO",
  "change-language.change": "Ändern",
  "change-language.heading": "Sprache ändern",
  "dialog.cancel": "Abbrechen",
  "dialog.close": "Schließen",
  "note.content-empty": "Diese Notiz hat noch keinen Inhalt. Klicke hier, um welchen hinzuzufügen",
  "dialog.create-one-note-per-line.confirm": "Notizen erstellen",
  "dialog.create-one-note-per-line.explainer": "Pro Zeile wird eine neue Notiz erstellt",
  "dialog.create-one-note-per-line.heading": "Eine Notiz pro Zeile erstellen",
  "dialog.create-one-note-per-line.please-wait": "Bitte warte, während die Notizen erstellt werden ...",
  "editor.add-links": "Notiz verbinden",
  "editor.cancel": "Abbrechen",
  "editor.create-linked-note": "Neue verlinkte Notiz",
  "editor.discard-changes-confirmation.confirm": "Verwerfen",
  "editor.discard-changes-confirmation.text": "Einige Änderungen wurden noch nicht gespeichert. Möchtest du diese verwerfen?",
  "editor.duplicate-note": "Notiz duplizieren",
  "editor.go-to-list": "Zur Liste",
  "editor.linked-notes": "Verbundene Notizen ({linkedNotes})",
  "editor.new-note": "Neue Notiz",
  "editor.no-notes-linked-yet": "Diese Notiz ist zu keinen weiteren Notizen verbunden.",
  "editor.no-unsaved-changes": "Keine ungespeicherten Änderungen",
  "editor.note-has-not-been-saved-yet": "Diese Notiz wurde noch nicht gespeichert",
  "editor.note-search-placeholder": "Notizen durchsuchen...",
  "editor.pin-note": "Anpinnen",
  "editor.remove-note": "Notiz löschen",
  "editor.remove-note.confirm.confirm": "Notiz löschen",
  "editor.remove-note.confirm.text": "Möchtest du diese Notiz wirklich löschen?",
  "editor.reveal-note-in-graph": "Zeige Notiz im Graph",
  "editor.save-anyway": "Speichern",
  "editor.save-note": "Notiz speichern",
  "editor.stats.creation-time": "Erstellt am",
  "editor.stats.files": "Dateien",
  "editor.stats.files.none": "Keine",
  "editor.stats.heading": "Metadaten",
  "editor.stats.id": "ID",
  "editor.stats.last-update-time": "Zuletzt aktualisiert",
  "editor.stats.number-of-blocks": "Blöcke",
  "editor.stats.number-of-characters": "Zeichen",
  "editor.stats.number-of-links": "Verbundene Notizen",
  "editor.stats.x-coordinate": "X-Koordinate",
  "editor.stats.y-coordinate": "Y-Koordinate",
  "editor.title-already-exists-confirmation": "Eine Notiz mit diesem Titel existiert bereits. Möchtest du diese Notiz mit dem gleichen Titel speichern?",
  "editor.unsaved-changes": "Ungespeicherte Änderungen",
  "editor.upload-file": "Datei hochladen",
  "export-database.export": "Exportieren",
  "export-database.file-size-written": "{fileSizeWritten} geschrieben.",
  "export-database.finished": "Datenbankexport abgeschlossen.",
  "export-database.graph-file-only": "Nur Graph-Datei exportieren (JSON)",
  "export-database.heading": "Datenbank exportieren",
  "export-database.please-wait": "Die Datenbank wird exportiert. Bitte warte...",
  "export-database.with-files": "Graph-Datei und alle anderen Dateien exportieren (ZIP)",
  "files.confirm-delete": "Möchtest du diese Datei wirklich löschen? Das kann nicht rückgängig gemacht werden.",
  "files.confirm-delete.confirm": "Datei löschen",
  "files.create-note-with-file": "Notiz mit dieser Datei erstellen",
  "files.dangling-files.explainer": "Nicht eingehangene Dateien sind Dateien, die in keiner Notiz benutzt werden.",
  "files.dangling-files.heading": "Nicht eingehangene Dateien ({danglingFiles})",
  "files.delete": "Löschen",
  "files.fetching": "Dateien werden geladen...",
  "files.files-heading": "Dateien ({numberOfFiles})",
  "files.show-all-files": "Zeige alle Dateien",
  "files.used-in": "Benutzt in",
  "files.used-in.none": "Diese Datei wird von keiner Notiz benutzt.",
  "graph.inflate-10%": "Graph um 10% aufblähen",
  "graph.initial-position-explainer": "Anfängliche Position für neue Notizen (kann woanders hin bewegt werden)",
  "graph.mode.default": "Standard",
  "graph.mode.hubs-only": "Nur Hubs",
  "graph.mode.no-labels": "Keine Beschriftungen",
  "graph.mode.voronoy": "Voronoy",
  "graph.mode.voronoy-hubs": "Voronoy (nur Hubs)",
  "graph.open-in-editor": "Notiz im Editor öffnen",
  "graph.save": "Speichern",
  "graph.search-placeholder": "Suchen...",
  "graph.select-note-before-opening": "Bitte wähle zuerst eine Notiz aus",
  "graph.select-only-one-note": "Bitte wähle nur eine Notiz aus, um sie zu öffnen.",
  "graph.toggle-text-rendering": "Notiz-Titel anzeigen/verbergen",
  "list.item.features.contains-audio": "Enthält Audio",
  "list.item.features.contains-code": "Enthält Code",
  "list.item.features.contains-documents": "Enthält Dokumente",
  "list.item.features.contains-images": "Enthält Bilder",
  "list.item.features.contains-links": "Enthält Weblinks",
  "list.item.features.contains-text": "Enthält Text",
  "list.item.features.contains-video": "Enthält Video",
  "list.item.file": "{files} Datei",
  "list.item.files": "{files} Dateien",
  "list.item.hub": "Hub",
  "list.item.links.currently-selected": "Diese Notiz ist momentan ausgewählt. Sie kann nicht mit sich selbst verbunden werden.",
  "list.item.links.link": "Mit ausgewählter Notiz verbinden",
  "list.item.links.linked-to-x-notes": "Diese Notiz ist mit ${numberOfLinkedNotes} anderen Notiz(en) verbunden.",
  "list.item.links.not-linked": "Nicht verbunden",
  "list.item.links.unlink": "Verbindung zu ausgewählter Notiz entfernen",
  "list.note-list": "Notiz-Liste",
  "list.pagination.next-page": "Nächste Seite",
  "list.pagination.previous-page": "Vorherige Seite",
  "list.refresh": "Liste aktualisieren",
  "list.search.placeholder": "Notizen durchsuchen...",
  "list.search.presets": "Such-Vorlagen",
  "list.search.presets.duplicates": "Duplikate",
  "list.search.presets.notes-with-audio": "Notizen mit Audio",
  "list.search.presets.notes-with-documents": "Notizen mit Dokumenten",
  "list.search.presets.notes-with-duplicate-titles": "Notizen mit gleichen Titeln",
  "list.search.presets.notes-with-duplicate-urls": "Notizen mit gleichen URLs",
  "list.search.presets.notes-with-images": "Notizen mit Bildern",
  "list.search.presets.notes-with-video": "Notizen mit Videos",
  "list.search.presets.untitled-notes": "Unbenannte Notizen",
  "list.search.x-note-found": "{number} Notiz gefunden",
  "list.search.x-notes-found": "{number} Notizen gefunden",
  "list.sort-mode.creation-date-ascending": "Zeitpunkt des Erstellens (aufsteigend)",
  "list.sort-mode.creation-date-descending": "Zeitpunkt des Erstellens (absteigend)",
  "list.sort-mode.number-of-chars-ascending": "Zeichenanzahl (aufsteigend)",
  "list.sort-mode.number-of-chars-descending": "Zeichenanzahl (absteigend)",
  "list.sort-mode.number-of-files-ascending": "Anzahl an Dateien (aufsteigend)",
  "list.sort-mode.number-of-files-descending": "Anzahl an Dateien (absteigend)",
  "list.sort-mode.number-of-links-ascending": "Anzahl verbundener Notizen (aufsteigend)",
  "list.sort-mode.number-of-links-descending": "Anzahl verbundener Notizen (absteigend)",
  "list.sort-mode.title-a-z": "Titel (A-Z)",
  "list.sort-mode.title-z-a": "Titel (Z-A)",
  "list.sort-mode.update-date-ascending": "Letzte Aktualisierung (aufsteigend)",
  "list.sort-mode.update-date-descending": "Letzte Aktualisierung (absteigend)",
  "list.status.busy": "Notizen werden geladen ...",
  "list.status.no-notes-found": "Keine Notizen gefunden",
  "list.status.too-short": "Bitte gib mindestens 3 Zeichen zum Suchen ein.",
  "list.untitled-note": "Unbenannte Notiz",
  "login.introduction": "Dein persönlicher Wissens-Graph",
  "login.local.already-created-database": "Du hast bereits eine lokale Datenbank erstellt, die du öffnen kannst.",
  "login.local.error-accessing-folder": "Es gab ein Problem beim Zugriff auf den Datenbankordner. Hast du ihn verschoben oder gelöscht?",
  "login.local.heading": "Lokale Datenbank",
  "login.local.open-database-x": "Öffne Datenbank {dbName}",
  "login.local.select-folder": "Datenbankordner auswählen",
  "login.local.select-folder.explainer": "Wähle einen Datenbankordner aus (wenn es darin keine Datenbank gibt, wird eine neue erstellt)",
  "login.local.unsupported": "Dein Browser unterstützt leider keine lokalen Datenbanken.",
  "login.logo.alt": "NENO Logo",
  "login.read-the-manual": "Lies das Benutzerhandbuch (englisch)",
  "login.server.heading": "Server-Datenbank",
  "login.server.invalid-credentials": "Die Kombination aus Benutzername, Passwort und 2FA-Token scheint nicht korrekt zu sein. Probier es noch einmal.",
  "login.server.mfa-token": "2FA-Token",
  "login.server.no-support": "Diese NENO-Instanz unterstützt nicht das Verbinden zu Server-Datenbanken. Du kannst jedoch %EXTERNAL_LINK[deinen eigenen NENO-Server aufsetzen](https://github.com/SebastianZimmer/neno).",
  "login.server.password": "Passwort",
  "login.server.server-error": "Etwas stimmt nicht mit dem Server. Wie wäre es, wenn du stattdessen eine lokale Datenbank erstellst?",
  "login.server.too-many-attempts": "Zu viele Login-Versuche. Bitte warte eine Weile und versuch es dann nochmal.",
  "login.server.trying-to-login": "Bitte warte ...",
  "login.server.username": "Benutzername",
  "menu.change-language": "Sprache ändern",
  "menu.create-one-note-per-line": "Eine Notiz pro Zeile erstellen",
  "menu.editor": "Editor",
  "menu.export-database": "Datenbank exportieren",
  "menu.files": "Dateien",
  "menu.graph": "Graph",
  "menu.logout": "Logout",
  "menu.note-list": "Liste",
  "menu.stats": "Statistiken",
  "editor.edit-note": "Notizinhalt bearbeiten",
  "editor.finish-editing": "Bearbeitung abschließen",
  "menu.switch-graphs": "Graph wechseln",
  "note.download-file": "Datei herunterladen",
  "stats.analysis": "Analyse",
  "stats.analysis.components": "%EXTERNAL_LINK[Komponenten](https://en.wikipedia.org/wiki/Component_(graph_theory%29)",
  "stats.analysis.components-with-more-than-one-node": "Komponenten mit mehr als einem Knoten",
  "stats.analysis.cyclomatic-number": "%EXTERNAL_LINK[Zyklomatische Zahl](https://en.wikipedia.org/wiki/Circuit_rank)",
  "stats.analysis.hubs": "Hubs (Notizen mit mehr als 4 Verbindungen)",
  "stats.analysis.links-edges": "Verbindungen/Kanten",
  "stats.analysis.meshedness": "Meshedness (Anzahl Verbindungen / maximal mögliche Anzahl an Verbindungen)",
  "stats.analysis.no-notes-yet": "Es sind noch keine Notizen vorhanden.",
  "stats.analysis.nodes-notes": "Notizen/Knoten",
  "stats.analysis.nodes-with-most-links": "Notizen mit den meisten Verbindungen",
  "stats.fetching": "Statistiken werden erstellt...",
  "stats.graph-stats": "Graph-Statistiken",
  "stats.loading-stats": "Statistiken werden geladen ...",
  "stats.metadata": "Metadaten",
  "stats.metadata.creation-time": "Erstellt am",
  "stats.metadata.graph-size-without-files": "Größe des Graphs (ohne Dateien)",
  "stats.metadata.id": "ID",
  "stats.metadata.number-of-files": "Dateien",
  "stats.metadata.pins": "Angepinnte Notizen",
  "stats.metadata.size-of-all-files": "Größe aller Dateien",
  "stats.metadata.type": "Typ",
  "stats.metadata.update-time": "Letzte Aktualisierung",
  "stats.number-of-links": "Verbindungen",
  "stats.number-of-notes": "Notizen",
  "stats.unlinked-notes": "Unverbundene Notizen",
  "switch-graphs.heading": "Graph wechseln",
  "switch-graphs.switch": "Wechseln"
}